{
    "tableName": "auth",
    "createOnConnect": true,
    "columns": [
        {
            "name": "id",
            "type": "serial",
            "required": true,
            "isUnique": false,
            "primary": true
        },
        {
            "name": "username",
            "type": "TEXT",
            "required": true,
            "isUnique": false,
            "primary": false
        },
        {
            "name": "password",
            "type": "TEXT",
            "required": false,
            "isUnique": false,
            "primary": false
        },
        {
            "name": "private_key",
            "type": "TEXT",
            "required": false,
            "isUnique": false,
            "primary": false
        },
        {
            "name": "created_at",
            "type": "TIMESTAMP",
            "required": true,
            "isUnique": false,
            "primary": false
        },
        {
            "name": "hash",
            "type": "text",
            "required": true,
            "isUnique": true,
            "primary": false
        },
        {
            "name": "created_by",
            "type": "text",
            "required": true,
            "isUnique": false,
            "primary": false
        }
    ]
}